{
  "cik": "0000723125",
  "name": "MICRON TECHNOLOGY INC",
  "last_refreshed": "2026-04-20",
  "annual": [
    {
      "period_end": "2025-08-28",
      "filing_date": "2025-10-03",
      "form": "10-K",
      "namespace": "us-gaap",
      "currency": "USD",
      "revenue_M": 37378,
      "rnd_M": 3798,
      "cost_of_revenue_M": 22505,
      "net_income_M": 8539,
      "capex_M": 15857,
      "operating_cash_flow_M": 17525,
      "operating_income_M": 9770,
      "sga_M": 1205,
      "cash_M": 9642,
      "total_debt_M": 11533,
      "total_assets_M": 82798,
      "tags_used": {
        "revenue": "us-gaap:RevenueFromContractWithCustomerExcludingAssessedTax",
        "rnd": "us-gaap:ResearchAndDevelopmentExpense",
        "cost_of_revenue": "us-gaap:CostOfGoodsAndServicesSold",
        "net_income": "us-gaap:NetIncomeLoss",
        "capex": "us-gaap:PaymentsToAcquirePropertyPlantAndEquipment",
        "operating_cash_flow": "us-gaap:NetCashProvidedByUsedInOperatingActivities",
        "operating_income": "us-gaap:OperatingIncomeLoss",
        "sga": "us-gaap:SellingGeneralAndAdministrativeExpense",
        "cash": "us-gaap:CashAndCashEquivalentsAtCarryingValue",
        "total_debt": "us-gaap:LongTermDebt",
        "total_assets": "us-gaap:Assets"
      }
    },
    {
      "period_end": "2024-08-29",
      "filing_date": "2024-10-04",
      "form": "10-K",
      "namespace": "us-gaap",
      "currency": "USD",
      "revenue_M": 25111,
      "rnd_M": 3430,
      "cost_of_revenue_M": 19498,
      "net_income_M": 778,
      "capex_M": 8386,
      "operating_cash_flow_M": 8507,
      "operating_income_M": 1304,
      "sga_M": 1129,
      "cash_M": 7041,
      "total_debt_M": 11343,
      "total_assets_M": 69416
    },
    {
      "period_end": "2023-08-31",
      "filing_date": "2023-10-06",
      "form": "10-K",
      "namespace": "us-gaap",
      "currency": "USD",
      "revenue_M": 15540,
      "rnd_M": 3114,
      "cost_of_revenue_M": 16956,
      "net_income_M": -5833,
      "capex_M": 7676,
      "operating_cash_flow_M": 1559,
      "operating_income_M": -5745,
      "sga_M": 920,
      "cash_M": 8577,
      "total_debt_M": 12049,
      "total_assets_M": 64254
    },
    {
      "period_end": "2022-09-01",
      "filing_date": "2022-10-07",
      "form": "10-K",
      "namespace": "us-gaap",
      "currency": "USD",
      "revenue_M": 30758,
      "rnd_M": 3116,
      "cost_of_revenue_M": 16860,
      "net_income_M": 8687,
      "capex_M": 12067,
      "operating_cash_flow_M": 15181,
      "operating_income_M": 9702,
      "sga_M": 1066,
      "cash_M": 8262,
      "total_debt_M": 6020,
      "total_assets_M": 66283
    },
    {
      "period_end": "2021-09-02",
      "filing_date": "2021-10-08",
      "form": "10-K",
      "namespace": "us-gaap",
      "currency": "USD",
      "revenue_M": 27705,
      "rnd_M": 2663,
      "cost_of_revenue_M": 17282,
      "net_income_M": 5861,
      "capex_M": 10030,
      "operating_cash_flow_M": 12468,
      "operating_income_M": 6283,
      "sga_M": 894,
      "cash_M": 7763,
      "total_debt_M": 5968,
      "total_assets_M": 58849
    },
    {
      "period_end": "2020-09-03",
      "filing_date": "2020-10-19",
      "form": "10-K",
      "namespace": "us-gaap",
      "currency": "USD",
      "revenue_M": 21435,
      "rnd_M": 2600,
      "cost_of_revenue_M": 14883,
      "net_income_M": 2687,
      "capex_M": 8223,
      "operating_cash_flow_M": 8306,
      "operating_income_M": 3003,
      "sga_M": 881,
      "cash_M": 7624,
      "total_debt_M": 6157,
      "total_assets_M": 53678
    },
    {
      "period_end": "2019-08-29",
      "filing_date": "2019-10-17",
      "form": "10-K",
      "namespace": "us-gaap",
      "currency": "USD",
      "revenue_M": 23406,
      "rnd_M": 2441,
      "cost_of_revenue_M": 12704,
      "net_income_M": 6313,
      "capex_M": 9780,
      "operating_cash_flow_M": 13189,
      "operating_income_M": 7376,
      "sga_M": 836,
      "cash_M": 7152,
      "total_debt_M": 4541,
      "total_assets_M": 48887
    },
    {
      "period_end": "2018-08-30",
      "filing_date": "2018-10-15",
      "form": "10-K",
      "namespace": "us-gaap",
      "currency": "USD",
      "revenue_M": 30391,
      "rnd_M": 2141,
      "cost_of_revenue_M": 12500,
      "net_income_M": 14135,
      "capex_M": 8879,
      "operating_cash_flow_M": 17400,
      "operating_income_M": 14994,
      "sga_M": 813,
      "cash_M": 6506,
      "total_debt_M": 3777,
      "total_assets_M": 43376
    },
    {
      "period_end": "2017-08-31",
      "filing_date": "2017-10-26",
      "form": "10-K",
      "namespace": "us-gaap",
      "currency": "USD",
      "revenue_M": 20322,
      "rnd_M": 1824,
      "cost_of_revenue_M": 11886,
      "net_income_M": 5089,
      "capex_M": 4734,
      "operating_cash_flow_M": 8153,
      "operating_income_M": 5868,
      "sga_M": 743,
      "cash_M": 5109,
      "total_debt_M": 9872,
      "total_assets_M": 35336
    }
  ],
  "quarterly": [
    {
      "period_end": "2026-02-26",
      "filing_date": "2026-03-19",
      "form": "10-Q",
      "namespace": "us-gaap",
      "currency": "USD",
      "revenue_M": 23860,
      "rnd_M": 1250,
      "cost_of_revenue_M": 6105,
      "net_income_M": 13785,
      "capex_M": 11776,
      "operating_cash_flow_M": 20314,
      "operating_income_M": 16135,
      "sga_M": 344,
      "cash_M": 13908,
      "total_debt_M": 9557,
      "total_assets_M": 101509,
      "tags_used": {
        "revenue": "us-gaap:RevenueFromContractWithCustomerExcludingAssessedTax",
        "rnd": "us-gaap:ResearchAndDevelopmentExpense",
        "cost_of_revenue": "us-gaap:CostOfGoodsAndServicesSold",
        "net_income": "us-gaap:NetIncomeLoss",
        "capex": "us-gaap:PaymentsToAcquirePropertyPlantAndEquipment",
        "operating_cash_flow": "us-gaap:NetCashProvidedByUsedInOperatingActivities",
        "operating_income": "us-gaap:OperatingIncomeLoss",
        "sga": "us-gaap:SellingGeneralAndAdministrativeExpense",
        "cash": "us-gaap:CashAndCashEquivalentsAtCarryingValue",
        "total_debt": "us-gaap:LongTermDebtAndCapitalLeaseObligations",
        "total_assets": "us-gaap:Assets"
      }
    },
    {
      "period_end": "2025-11-27",
      "filing_date": "2025-12-18",
      "form": "10-Q",
      "namespace": "us-gaap",
      "currency": "USD",
      "revenue_M": 13643,
      "rnd_M": 1171,
      "cost_of_revenue_M": 5997,
      "net_income_M": 5240,
      "capex_M": 5389,
      "operating_cash_flow_M": 8411,
      "operating_income_M": 6136,
      "sga_M": 337,
      "cash_M": 9731,
      "total_debt_M": 8844,
      "total_assets_M": 85971
    },
    {
      "period_end": "2025-05-29",
      "filing_date": "2025-06-26",
      "form": "10-Q",
      "namespace": "us-gaap",
      "currency": "USD",
      "revenue_M": 9301,
      "rnd_M": 965,
      "cost_of_revenue_M": 5793,
      "net_income_M": 1885,
      "capex_M": 10199,
      "operating_cash_flow_M": 11795,
      "operating_income_M": 2169,
      "sga_M": 318,
      "cash_M": 10163,
      "total_debt_M": 12434,
      "total_assets_M": 78397
    },
    {
      "period_end": "2025-02-27",
      "filing_date": "2025-03-21",
      "form": "10-Q",
      "namespace": "us-gaap",
      "currency": "USD",
      "revenue_M": 8053,
      "rnd_M": 898,
      "cost_of_revenue_M": 5090,
      "net_income_M": 1583,
      "capex_M": 7261,
      "operating_cash_flow_M": 7186,
      "operating_income_M": 1773,
      "sga_M": 285,
      "cash_M": 7552,
      "total_debt_M": 11541,
      "total_assets_M": 73053
    },
    {
      "period_end": "2024-11-28",
      "filing_date": "2024-12-19",
      "form": "10-Q",
      "namespace": "us-gaap",
      "currency": "USD",
      "revenue_M": 8709,
      "rnd_M": 888,
      "cost_of_revenue_M": 5361,
      "net_income_M": 1870,
      "capex_M": 3206,
      "operating_cash_flow_M": 3244,
      "operating_income_M": 2174,
      "sga_M": 288,
      "cash_M": 6693,
      "total_debt_M": 11306,
      "total_assets_M": 71461
    },
    {
      "period_end": "2024-05-30",
      "filing_date": "2024-06-27",
      "form": "10-Q",
      "namespace": "us-gaap",
      "currency": "USD",
      "revenue_M": 6811,
      "rnd_M": 850,
      "cost_of_revenue_M": 4979,
      "net_income_M": 332,
      "capex_M": 5266,
      "operating_cash_flow_M": 5102,
      "operating_income_M": 719,
      "sga_M": 291,
      "cash_M": 7594,
      "total_debt_M": 11332,
      "total_assets_M": 66255
    },
    {
      "period_end": "2024-02-29",
      "filing_date": "2024-03-21",
      "form": "10-Q",
      "namespace": "us-gaap",
      "currency": "USD",
      "revenue_M": 5824,
      "rnd_M": 832,
      "cost_of_revenue_M": 4745,
      "net_income_M": 793,
      "capex_M": 3180,
      "operating_cash_flow_M": 2620,
      "operating_income_M": 191,
      "sga_M": 280,
      "cash_M": 8016,
      "total_debt_M": 12018,
      "total_assets_M": 65718
    },
    {
      "period_end": "2023-11-30",
      "filing_date": "2023-12-21",
      "form": "10-Q",
      "namespace": "us-gaap",
      "currency": "USD",
      "revenue_M": 4726,
      "rnd_M": 845,
      "cost_of_revenue_M": 4761,
      "net_income_M": -1234,
      "capex_M": 1796,
      "operating_cash_flow_M": 1401,
      "operating_income_M": -1128,
      "sga_M": 263,
      "cash_M": 8075,
      "total_debt_M": 12024,
      "total_assets_M": 63776
    },
    {
      "period_end": "2023-06-01",
      "filing_date": "2023-06-29",
      "form": "10-Q",
      "namespace": "us-gaap",
      "currency": "USD",
      "revenue_M": 3752,
      "rnd_M": 758,
      "cost_of_revenue_M": 4420,
      "net_income_M": -1896,
      "capex_M": 6215,
      "operating_cash_flow_M": 1310,
      "operating_income_M": -1761,
      "sga_M": 219,
      "cash_M": 9298,
      "total_debt_M": 12074,
      "total_assets_M": 65680
    },
    {
      "period_end": "2023-03-02",
      "filing_date": "2023-03-29",
      "form": "10-Q",
      "namespace": "us-gaap",
      "currency": "USD",
      "revenue_M": 3693,
      "rnd_M": 788,
      "cost_of_revenue_M": 4899,
      "net_income_M": -2312,
      "capex_M": 4654,
      "operating_cash_flow_M": 1286,
      "operating_income_M": -2303,
      "sga_M": 231,
      "cash_M": 9798,
      "total_debt_M": 11203,
      "total_assets_M": 66520
    },
    {
      "period_end": "2022-12-01",
      "filing_date": "2022-12-22",
      "form": "10-Q",
      "namespace": "us-gaap",
      "currency": "USD",
      "revenue_M": 4085,
      "rnd_M": 849,
      "cost_of_revenue_M": 3192,
      "net_income_M": -195,
      "capex_M": 2449,
      "operating_cash_flow_M": 943,
      "operating_income_M": -209,
      "sga_M": 251,
      "cash_M": 9574,
      "total_debt_M": 9351,
      "total_assets_M": 67874
    },
    {
      "period_end": "2022-06-02",
      "filing_date": "2022-07-01",
      "form": "10-Q",
      "namespace": "us-gaap",
      "currency": "USD",
      "revenue_M": 8642,
      "rnd_M": 773,
      "cost_of_revenue_M": 4607,
      "net_income_M": 2626,
      "capex_M": 8454,
      "operating_cash_flow_M": 11404,
      "operating_income_M": 3004,
      "sga_M": 264,
      "cash_M": 9157,
      "total_debt_M": 6034,
      "total_assets_M": 65296
    },
    {
      "period_end": "2022-03-03",
      "filing_date": "2022-03-30",
      "form": "10-Q",
      "namespace": "us-gaap",
      "currency": "USD",
      "revenue_M": 7786,
      "rnd_M": 792,
      "cost_of_revenue_M": 4110,
      "net_income_M": 2263,
      "capex_M": 5876,
      "operating_cash_flow_M": 7566,
      "operating_income_M": 2546,
      "sga_M": 263,
      "cash_M": 9116,
      "total_debt_M": 6081,
      "total_assets_M": 63696
    },
    {
      "period_end": "2021-12-02",
      "filing_date": "2022-01-06",
      "form": "10-Q",
      "namespace": "us-gaap",
      "currency": "USD",
      "revenue_M": 7687,
      "rnd_M": 712,
      "cost_of_revenue_M": 4122,
      "net_income_M": 2306,
      "capex_M": 3265,
      "operating_cash_flow_M": 3938,
      "operating_income_M": 2631,
      "sga_M": 259,
      "cash_M": 8680,
      "total_debt_M": 6096,
      "total_assets_M": 61246
    },
    {
      "period_end": "2021-06-03",
      "filing_date": "2021-07-01",
      "form": "10-Q",
      "namespace": "us-gaap",
      "currency": "USD",
      "revenue_M": 7422,
      "rnd_M": 670,
      "cost_of_revenue_M": 4296,
      "net_income_M": 1735,
      "capex_M": 8015,
      "operating_cash_flow_M": 8584,
      "operating_income_M": 1799,
      "sga_M": 230,
      "cash_M": 7759,
      "total_debt_M": 6418,
      "total_assets_M": 55943
    },
    {
      "period_end": "2021-03-04",
      "filing_date": "2021-04-01",
      "form": "10-Q",
      "namespace": "us-gaap",
      "currency": "USD",
      "revenue_M": 6236,
      "rnd_M": 641,
      "cost_of_revenue_M": 4587,
      "net_income_M": 603,
      "capex_M": 5756,
      "operating_cash_flow_M": 5024,
      "operating_income_M": 663,
      "sga_M": 214,
      "cash_M": 6507,
      "total_debt_M": 6298,
      "total_assets_M": 54135
    },
    {
      "period_end": "2020-12-03",
      "filing_date": "2021-01-08",
      "form": "10-Q",
      "namespace": "us-gaap",
      "currency": "USD",
      "revenue_M": 5773,
      "rnd_M": 647,
      "cost_of_revenue_M": 4037,
      "net_income_M": 803,
      "capex_M": 2738,
      "operating_cash_flow_M": 1967,
      "operating_income_M": 866,
      "sga_M": 214,
      "cash_M": 5985,
      "total_debt_M": 6356,
      "total_assets_M": 53691
    },
    {
      "period_end": "2020-05-28",
      "filing_date": "2020-06-29",
      "form": "10-Q",
      "namespace": "us-gaap",
      "currency": "USD",
      "revenue_M": 5438,
      "rnd_M": 649,
      "cost_of_revenue_M": 3675,
      "net_income_M": 803,
      "capex_M": 5943,
      "operating_cash_flow_M": 6035,
      "operating_income_M": 888,
      "sga_M": 216,
      "cash_M": 8267,
      "total_debt_M": 6356,
      "total_assets_M": 52005
    },
    {
      "period_end": "2020-02-27",
      "filing_date": "2020-03-26",
      "form": "10-Q",
      "namespace": "us-gaap",
      "currency": "USD",
      "revenue_M": 4797,
      "rnd_M": 681,
      "cost_of_revenue_M": 3442,
      "net_income_M": 405,
      "capex_M": 3999,
      "operating_cash_flow_M": 4012,
      "operating_income_M": 440,
      "sga_M": 223,
      "cash_M": 7118,
      "total_debt_M": 5188,
      "total_assets_M": 49648
    },
    {
      "period_end": "2019-11-28",
      "filing_date": "2019-12-20",
      "form": "10-Q",
      "namespace": "us-gaap",
      "currency": "USD",
      "revenue_M": 5144,
      "rnd_M": 640,
      "cost_of_revenue_M": 3778,
      "net_income_M": 491,
      "capex_M": 1943,
      "operating_cash_flow_M": 2011,
      "operating_income_M": 518,
      "sga_M": 211,
      "cash_M": 6969,
      "total_debt_M": 5188,
      "total_assets_M": 49649
    },
    {
      "period_end": "2019-05-30",
      "filing_date": "2019-06-26",
      "form": "10-Q",
      "namespace": "us-gaap",
      "currency": "USD",
      "revenue_M": 4788,
      "rnd_M": 606,
      "cost_of_revenue_M": 2960,
      "net_income_M": 840,
      "capex_M": 7752,
      "operating_cash_flow_M": 10956,
      "operating_income_M": 1010,
      "sga_M": 206,
      "cash_M": 5157,
      "total_debt_M": 3563,
      "total_assets_M": 46288
    },
    {
      "period_end": "2019-02-28",
      "filing_date": "2019-03-21",
      "form": "10-Q",
      "namespace": "us-gaap",
      "currency": "USD",
      "revenue_M": 5835,
      "rnd_M": 601,
      "cost_of_revenue_M": 2971,
      "net_income_M": 1619,
      "capex_M": 5349,
      "operating_cash_flow_M": 8245,
      "operating_income_M": 1957,
      "sga_M": 209,
      "cash_M": 6353,
      "total_debt_M": 3604,
      "total_assets_M": 47487
    },
    {
      "period_end": "2018-11-29",
      "filing_date": "2018-12-19",
      "form": "10-Q",
      "namespace": "us-gaap",
      "currency": "USD",
      "revenue_M": 7913,
      "rnd_M": 611,
      "cost_of_revenue_M": 3298,
      "net_income_M": 3293,
      "capex_M": 2700,
      "operating_cash_flow_M": 4810,
      "operating_income_M": 3759,
      "sga_M": 209,
      "cash_M": 4447,
      "total_debt_M": 3734,
      "total_assets_M": 44595
    },
    {
      "period_end": "2018-05-31",
      "filing_date": "2018-06-22",
      "form": "10-Q",
      "namespace": "us-gaap",
      "currency": "USD",
      "revenue_M": 7797,
      "rnd_M": 603,
      "cost_of_revenue_M": 3074,
      "net_income_M": 3823,
      "capex_M": 6628,
      "operating_cash_flow_M": 12245,
      "operating_income_M": 3953,
      "sga_M": 211,
      "cash_M": 6808,
      "total_debt_M": 5890,
      "total_assets_M": 41845
    },
    {
      "period_end": "2018-03-01",
      "filing_date": "2018-03-23",
      "form": "10-Q",
      "namespace": "us-gaap",
      "currency": "USD",
      "revenue_M": 7351,
      "rnd_M": 523,
      "cost_of_revenue_M": 3081,
      "net_income_M": 3309,
      "capex_M": 4217,
      "operating_cash_flow_M": 7984,
      "operating_income_M": 3567,
      "sga_M": 196,
      "cash_M": 7828,
      "total_debt_M": 7802,
      "total_assets_M": 41263
    },
    {
      "period_end": "2017-11-30",
      "filing_date": "2017-12-20",
      "form": "10-Q",
      "namespace": "us-gaap",
      "currency": "USD",
      "revenue_M": 6803,
      "rnd_M": 448,
      "cost_of_revenue_M": 3056,
      "net_income_M": 2678,
      "capex_M": 1956,
      "operating_cash_flow_M": 3636,
      "operating_income_M": 3097,
      "sga_M": 191,
      "cash_M": 6008,
      "total_debt_M": 7644,
      "total_assets_M": 37191
    },
    {
      "period_end": "2017-06-01",
      "filing_date": "2017-06-30",
      "form": "10-Q",
      "namespace": "us-gaap",
      "currency": "USD",
      "revenue_M": 5566,
      "rnd_M": 434,
      "cost_of_revenue_M": 2957,
      "net_income_M": 1647,
      "capex_M": 3469,
      "operating_cash_flow_M": 4950,
      "operating_income_M": 1963,
      "sga_M": 204,
      "cash_M": 4048,
      "total_debt_M": 10485,
      "total_assets_M": 33267
    },
    {
      "period_end": "2017-03-02",
      "filing_date": "2017-03-28",
      "form": "10-Q",
      "namespace": "us-gaap",
      "currency": "USD",
      "revenue_M": 4648,
      "rnd_M": 473,
      "cost_of_revenue_M": 2944,
      "net_income_M": 894,
      "capex_M": 2428,
      "operating_cash_flow_M": 2543,
      "operating_income_M": 1044,
      "sga_M": 187,
      "cash_M": 3633,
      "total_debt_M": 11308,
      "total_assets_M": 32355
    }
  ]
}