{
  "cik": "0001610520",
  "name": "UBS Group AG",
  "last_refreshed": "2026-04-20",
  "annual": [
    {
      "period_end": "2025-12-31",
      "filing_date": "2026-03-09",
      "form": "20-F",
      "namespace": "",
      "currency": "",
      "revenue_M": null,
      "rnd_M": null,
      "cost_of_revenue_M": null,
      "net_income_M": 7797,
      "capex_M": null,
      "operating_cash_flow_M": 21851,
      "sga_M": null,
      "cash_M": 231375,
      "total_debt_M": null,
      "total_assets_M": 1617427,
      "tags_used": {
        "net_income": "ifrs-full:ProfitLoss",
        "operating_cash_flow": "ifrs-full:CashFlowsFromUsedInOperatingActivities",
        "cash": "ifrs-full:CashAndCashEquivalents",
        "total_assets": "ifrs-full:Assets"
      }
    },
    {
      "period_end": "2024-12-31",
      "filing_date": "2025-03-17",
      "form": "20-F",
      "namespace": "",
      "currency": "",
      "revenue_M": null,
      "rnd_M": null,
      "cost_of_revenue_M": null,
      "net_income_M": 5146,
      "capex_M": null,
      "operating_cash_flow_M": 3279,
      "sga_M": null,
      "cash_M": 244090,
      "total_debt_M": null,
      "total_assets_M": 1565028
    },
    {
      "period_end": "2023-12-31",
      "filing_date": "2024-03-28",
      "form": "20-F",
      "namespace": "",
      "currency": "",
      "revenue_M": null,
      "rnd_M": null,
      "cost_of_revenue_M": null,
      "net_income_M": 27382,
      "capex_M": null,
      "operating_cash_flow_M": 86068,
      "sga_M": null,
      "cash_M": 340311,
      "total_debt_M": null,
      "total_assets_M": 1717246
    },
    {
      "period_end": "2022-12-31",
      "filing_date": "2023-03-06",
      "form": "20-F",
      "namespace": "",
      "currency": "",
      "revenue_M": null,
      "rnd_M": null,
      "cost_of_revenue_M": null,
      "net_income_M": 7661,
      "capex_M": null,
      "operating_cash_flow_M": 14647,
      "sga_M": null,
      "cash_M": 195321,
      "total_debt_M": null,
      "total_assets_M": 1104364
    },
    {
      "period_end": "2021-12-31",
      "filing_date": "2022-03-07",
      "form": "20-F",
      "namespace": "ifrs-full",
      "currency": "USD",
      "revenue_M": 35393,
      "rnd_M": null,
      "cost_of_revenue_M": null,
      "net_income_M": 7486,
      "capex_M": null,
      "operating_cash_flow_M": 31425,
      "sga_M": null,
      "cash_M": 207875,
      "total_debt_M": null,
      "total_assets_M": 1117182
    },
    {
      "period_end": "2020-12-31",
      "filing_date": "2021-03-05",
      "form": "20-F",
      "namespace": "ifrs-full",
      "currency": "USD",
      "revenue_M": 33084,
      "rnd_M": null,
      "cost_of_revenue_M": null,
      "net_income_M": 6572,
      "capex_M": null,
      "operating_cash_flow_M": 36958,
      "sga_M": null,
      "cash_M": 173531,
      "total_debt_M": null,
      "total_assets_M": 1125765
    },
    {
      "period_end": "2019-12-31",
      "filing_date": "2020-03-03",
      "form": "20-F",
      "namespace": "ifrs-full",
      "currency": "USD",
      "revenue_M": 28967,
      "rnd_M": null,
      "cost_of_revenue_M": null,
      "net_income_M": 4310,
      "capex_M": null,
      "operating_cash_flow_M": 19705,
      "sga_M": null,
      "cash_M": 119873,
      "total_debt_M": null,
      "total_assets_M": 972183
    },
    {
      "period_end": "2018-12-31",
      "filing_date": "2019-03-15",
      "form": "20-F",
      "namespace": "ifrs-full",
      "currency": "USD",
      "revenue_M": 30330,
      "rnd_M": null,
      "cost_of_revenue_M": null,
      "net_income_M": 4522,
      "capex_M": null,
      "operating_cash_flow_M": 28913,
      "sga_M": null,
      "cash_M": 126079,
      "total_debt_M": null,
      "total_assets_M": 958489
    },
    {
      "period_end": "2017-12-31",
      "filing_date": "2018-03-09",
      "form": "20-F",
      "namespace": "ifrs-full",
      "currency": "CHF",
      "revenue_M": 29195,
      "rnd_M": null,
      "cost_of_revenue_M": null,
      "net_income_M": 1128,
      "capex_M": null,
      "operating_cash_flow_M": -50911,
      "sga_M": null,
      "cash_M": 102200,
      "total_debt_M": null,
      "total_assets_M": 915642
    },
    {
      "period_end": "2016-12-31",
      "filing_date": "2017-03-10",
      "form": "20-F",
      "namespace": "ifrs-full",
      "currency": "CHF",
      "revenue_M": 28357,
      "rnd_M": null,
      "cost_of_revenue_M": null,
      "net_income_M": 3286,
      "capex_M": null,
      "operating_cash_flow_M": -16457,
      "sga_M": null,
      "cash_M": 121138,
      "total_debt_M": null,
      "total_assets_M": 935016
    },
    {
      "period_end": "2015-12-31",
      "filing_date": "2016-03-18",
      "form": "20-F",
      "namespace": "ifrs-full",
      "currency": "CHF",
      "revenue_M": 30722,
      "rnd_M": null,
      "cost_of_revenue_M": null,
      "net_income_M": 6386,
      "capex_M": null,
      "operating_cash_flow_M": 3109,
      "sga_M": null,
      "cash_M": 103044,
      "total_debt_M": null,
      "total_assets_M": 942819
    }
  ],
  "quarterly": [
    {
      "period_end": "2025-12-31",
      "currency": "USD",
      "revenue_M": 12199.0,
      "rnd_M": null,
      "cost_of_revenue_M": null,
      "net_income_M": 1199.0
    },
    {
      "period_end": "2025-09-30",
      "currency": "USD",
      "revenue_M": 11938.0,
      "rnd_M": null,
      "cost_of_revenue_M": null,
      "net_income_M": 2481.0
    },
    {
      "period_end": "2025-06-30",
      "currency": "USD",
      "revenue_M": 11499.0,
      "rnd_M": null,
      "cost_of_revenue_M": null,
      "net_income_M": 2395.0
    },
    {
      "period_end": "2025-03-31",
      "currency": "USD",
      "revenue_M": 11741.0,
      "rnd_M": null,
      "cost_of_revenue_M": null,
      "net_income_M": 1692.0
    },
    {
      "period_end": "2024-12-31",
      "currency": "USD",
      "revenue_M": 11060.0,
      "rnd_M": null,
      "cost_of_revenue_M": null,
      "net_income_M": 770.0
    },
    {
      "period_end": "2024-09-30",
      "currency": "USD",
      "revenue_M": null,
      "rnd_M": null,
      "cost_of_revenue_M": null,
      "net_income_M": null
    }
  ]
}