{
  "cik": "0001594805",
  "name": "Shopify Inc.",
  "last_refreshed": "2026-04-20",
  "annual": [
    {
      "period_end": "2025-12-31",
      "filing_date": "2026-02-11",
      "form": "10-K",
      "namespace": "us-gaap",
      "currency": "USD",
      "revenue_M": 11556,
      "rnd_M": 1536,
      "cost_of_revenue_M": 6001,
      "net_income_M": 1231,
      "capex_M": 26,
      "operating_cash_flow_M": 2033,
      "operating_income_M": 1468,
      "sga_M": 471,
      "cash_M": 1545,
      "total_debt_M": null,
      "total_assets_M": 15189,
      "tags_used": {
        "revenue": "us-gaap:Revenues",
        "rnd": "us-gaap:ResearchAndDevelopmentExpense",
        "cost_of_revenue": "us-gaap:CostOfGoodsAndServicesSold",
        "net_income": "us-gaap:NetIncomeLoss",
        "capex": "us-gaap:PaymentsToAcquirePropertyPlantAndEquipment",
        "operating_cash_flow": "us-gaap:NetCashProvidedByUsedInOperatingActivities",
        "operating_income": "us-gaap:OperatingIncomeLoss",
        "sga": "us-gaap:GeneralAndAdministrativeExpense",
        "cash": "us-gaap:CashAndCashEquivalentsAtCarryingValue",
        "total_assets": "us-gaap:Assets"
      }
    },
    {
      "period_end": "2024-12-31",
      "filing_date": "2025-04-29",
      "form": "10-K",
      "namespace": "us-gaap",
      "currency": "USD",
      "revenue_M": 8880,
      "rnd_M": 1367,
      "cost_of_revenue_M": 4408,
      "net_income_M": 2019,
      "capex_M": 19,
      "operating_cash_flow_M": 1616,
      "operating_income_M": 1075,
      "sga_M": 410,
      "cash_M": 1498,
      "total_debt_M": null,
      "total_assets_M": 13924,
      "amended": true
    },
    {
      "period_end": "2024-12-31",
      "filing_date": "2025-02-11",
      "form": "10-K",
      "namespace": "us-gaap",
      "currency": "USD",
      "revenue_M": 8880,
      "rnd_M": 1367,
      "cost_of_revenue_M": 4408,
      "net_income_M": 2019,
      "capex_M": 19,
      "operating_cash_flow_M": 1616,
      "operating_income_M": 1075,
      "sga_M": 410,
      "cash_M": 1498,
      "total_debt_M": null,
      "total_assets_M": 13924
    },
    {
      "period_end": "2023-12-31",
      "filing_date": "2024-02-13",
      "form": "40-F",
      "namespace": "us-gaap",
      "currency": "USD",
      "revenue_M": 7060,
      "rnd_M": 1730,
      "cost_of_revenue_M": 3545,
      "net_income_M": 132,
      "capex_M": 39,
      "operating_cash_flow_M": 944,
      "operating_income_M": -1418,
      "sga_M": 491,
      "cash_M": 1413,
      "total_debt_M": null,
      "total_assets_M": 11299
    },
    {
      "period_end": "2022-12-31",
      "filing_date": "2023-02-16",
      "form": "40-F",
      "namespace": "us-gaap",
      "currency": "USD",
      "revenue_M": 5600,
      "rnd_M": 1503,
      "cost_of_revenue_M": 2846,
      "net_income_M": -3460,
      "capex_M": 50,
      "operating_cash_flow_M": -136,
      "operating_income_M": -822,
      "sga_M": 708,
      "cash_M": 1649,
      "total_debt_M": null,
      "total_assets_M": 10757
    },
    {
      "period_end": "2021-12-31",
      "filing_date": "2022-02-16",
      "form": "40-F",
      "namespace": "us-gaap",
      "currency": "USD",
      "revenue_M": 4612,
      "rnd_M": 854,
      "cost_of_revenue_M": 2131,
      "net_income_M": 2915,
      "capex_M": 51,
      "operating_cash_flow_M": 536,
      "operating_income_M": 269,
      "sga_M": 375,
      "cash_M": 2503,
      "total_debt_M": null,
      "total_assets_M": 13340
    },
    {
      "period_end": "2020-12-31",
      "filing_date": "2021-02-17",
      "form": "40-F",
      "namespace": "us-gaap",
      "currency": "USD",
      "revenue_M": 2929,
      "rnd_M": 552,
      "cost_of_revenue_M": 1388,
      "net_income_M": 320,
      "capex_M": 42,
      "operating_cash_flow_M": 425,
      "operating_income_M": 90,
      "sga_M": 245,
      "cash_M": 2704,
      "total_debt_M": null,
      "total_assets_M": 7763
    },
    {
      "period_end": "2019-12-31",
      "filing_date": "2020-02-12",
      "form": "40-F",
      "namespace": "us-gaap",
      "currency": "USD",
      "revenue_M": 1578,
      "rnd_M": 355,
      "cost_of_revenue_M": 713,
      "net_income_M": -125,
      "capex_M": 57,
      "operating_cash_flow_M": 71,
      "operating_income_M": -141,
      "sga_M": 154,
      "cash_M": 650,
      "total_debt_M": null,
      "total_assets_M": 3489
    },
    {
      "period_end": "2018-12-31",
      "filing_date": "2019-02-12",
      "form": "40-F",
      "namespace": "us-gaap",
      "currency": "USD",
      "revenue_M": 1073,
      "rnd_M": 231,
      "cost_of_revenue_M": 477,
      "net_income_M": -65,
      "capex_M": 28,
      "operating_cash_flow_M": 9,
      "operating_income_M": -92,
      "sga_M": 107,
      "cash_M": 411,
      "total_debt_M": null,
      "total_assets_M": 2255
    },
    {
      "period_end": "2017-12-31",
      "filing_date": "2018-02-15",
      "form": "40-F",
      "namespace": "us-gaap",
      "currency": "USD",
      "revenue_M": 673,
      "rnd_M": 136,
      "cost_of_revenue_M": 293,
      "net_income_M": -40,
      "capex_M": 20,
      "operating_cash_flow_M": 8,
      "operating_income_M": -49,
      "sga_M": 68,
      "cash_M": 142,
      "total_debt_M": null,
      "total_assets_M": 1114
    },
    {
      "period_end": "2016-12-31",
      "filing_date": "2017-02-15",
      "form": "40-F",
      "namespace": "",
      "currency": "",
      "revenue_M": null,
      "rnd_M": 74,
      "cost_of_revenue_M": null,
      "net_income_M": -35,
      "capex_M": 24,
      "operating_cash_flow_M": 14,
      "operating_income_M": -37,
      "sga_M": 43,
      "cash_M": 84,
      "total_debt_M": null,
      "total_assets_M": 491
    },
    {
      "period_end": "2015-12-31",
      "filing_date": "2016-02-17",
      "form": "20-F",
      "namespace": "",
      "currency": "",
      "revenue_M": null,
      "rnd_M": 40,
      "cost_of_revenue_M": null,
      "net_income_M": -19,
      "capex_M": 17,
      "operating_cash_flow_M": 16,
      "operating_income_M": -18,
      "sga_M": 21,
      "cash_M": 110,
      "total_debt_M": null,
      "total_assets_M": 244
    }
  ],
  "quarterly": [
    {
      "period_end": "2025-09-30",
      "revenue": 2844000000,
      "net_income": 264000000,
      "rd_expense": 375000000
    },
    {
      "period_end": "2025-09-30",
      "filing_date": "2025-11-04",
      "form": "10-Q",
      "namespace": "us-gaap",
      "currency": "USD",
      "revenue_M": 2844,
      "rnd_M": 375,
      "cost_of_revenue_M": 1453,
      "net_income_M": 264,
      "capex_M": 6,
      "operating_cash_flow_M": 513,
      "operating_income_M": 343,
      "sga_M": 115,
      "cash_M": 2414,
      "total_debt_M": null,
      "total_assets_M": 15039,
      "tags_used": {
        "revenue": "us-gaap:Revenues",
        "rnd": "us-gaap:ResearchAndDevelopmentExpense",
        "cost_of_revenue": "us-gaap:CostOfGoodsAndServicesSold",
        "net_income": "us-gaap:NetIncomeLoss",
        "capex": "us-gaap:PaymentsToAcquirePropertyPlantAndEquipment",
        "operating_cash_flow": "us-gaap:NetCashProvidedByUsedInOperatingActivities",
        "operating_income": "us-gaap:OperatingIncomeLoss",
        "sga": "us-gaap:GeneralAndAdministrativeExpense",
        "cash": "us-gaap:CashAndCashEquivalentsAtCarryingValue",
        "total_assets": "us-gaap:Assets"
      }
    },
    {
      "period_end": "2025-06-30",
      "revenue": 2680000000,
      "net_income": 906000000,
      "rd_expense": 394000000
    },
    {
      "period_end": "2025-06-30",
      "filing_date": "2025-08-06",
      "form": "10-Q",
      "namespace": "us-gaap",
      "currency": "USD",
      "revenue_M": 2680,
      "rnd_M": 394,
      "cost_of_revenue_M": 1378,
      "net_income_M": 906,
      "capex_M": 6,
      "operating_cash_flow_M": 428,
      "operating_income_M": 291,
      "sga_M": 122,
      "cash_M": 1542,
      "total_debt_M": null,
      "total_assets_M": 14561
    },
    {
      "period_end": "2025-03-31",
      "revenue": 2360000000,
      "net_income": -682000000,
      "rd_expense": 377000000
    },
    {
      "period_end": "2025-03-31",
      "filing_date": "2025-05-08",
      "form": "10-Q",
      "namespace": "us-gaap",
      "currency": "USD",
      "revenue_M": 2360,
      "rnd_M": 377,
      "cost_of_revenue_M": 1191,
      "net_income_M": -682,
      "capex_M": 4,
      "operating_cash_flow_M": 367,
      "operating_income_M": 203,
      "sga_M": 109,
      "cash_M": 1309,
      "total_debt_M": null,
      "total_assets_M": 13400
    },
    {
      "period_end": "2024-09-30",
      "revenue": 2162000000,
      "net_income": 828000000,
      "rd_expense": 332000000
    },
    {
      "period_end": "2024-06-30",
      "revenue": 2045000000,
      "net_income": 171000000,
      "rd_expense": 349000000
    },
    {
      "period_end": "2024-03-31",
      "revenue": 1861000000,
      "net_income": -273000000,
      "rd_expense": 335000000
    }
  ]
}